graphio/__init__.py
graphio/utils.py
graphio/bulk/__init__.py
graphio/bulk/nodeset.py
graphio/bulk/query_utils.py
graphio/bulk/relationshipset.py
graphio/ogm/__init__.py
graphio/ogm/model.py
graphio/ogm/query_utils.py
graphio-0.20.dist-info/licenses/LICENSE
graphio-0.20.dist-info/METADATA
graphio-0.20.dist-info/WHEEL
graphio-0.20.dist-info/top_level.txt
graphio-0.20.dist-info/RECORD
