Metadata-Version: 2.4
Name: graphio
Version: 0.20
Summary: OGM and data loader for Neo4j.
Author: Martin Preusse
License-Expression: Apache-2.0
Project-URL: Homepage, https://github.com/kaiserpreusse/graphio
Project-URL: Documentation, https://graphio.readthedocs.io/
Project-URL: Repository, https://github.com/kaiserpreusse/graphio
Project-URL: Issues, https://github.com/kaiserpreusse/graphio/issues
Keywords: NEO4J
Classifier: Programming Language :: Python
Classifier: Programming Language :: Python :: 3
Classifier: Programming Language :: Python :: 3.10
Classifier: Programming Language :: Python :: 3.11
Classifier: Programming Language :: Python :: 3.12
Classifier: Programming Language :: Python :: 3.13
Classifier: Programming Language :: Python :: 3.14
Classifier: Intended Audience :: Developers
Requires-Python: >=3.10
License-File: LICENSE
Requires-Dist: neo4j>=5.25.0
Requires-Dist: pydantic<3,>=2.12
Provides-Extra: docs
Requires-Dist: mkdocs; extra == "docs"
Requires-Dist: mkdocs-material; extra == "docs"
Requires-Dist: mkdocstrings-python; extra == "docs"
Requires-Dist: pymdown-extensions; extra == "docs"
Provides-Extra: dev
Requires-Dist: pytest; extra == "dev"
Requires-Dist: hypothesis; extra == "dev"
Requires-Dist: mkdocs-material; extra == "dev"
Requires-Dist: mkdocstrings-python; extra == "dev"
Requires-Dist: ruff; extra == "dev"
Dynamic: license-file
